sprint_datapusher/__init__.py
sprint_datapusher/datapusher.py
sprint_datapusher-0.1.2.dist-info/entry_points.txt
sprint_datapusher-0.1.2.dist-info/LICENSE
sprint_datapusher-0.1.2.dist-info/WHEEL
sprint_datapusher-0.1.2.dist-info/METADATA
sprint_datapusher-0.1.2.dist-info/RECORD
