Metadata-Version: 2.1
Name: sprint-datapusher
Version: 0.1.2
Summary: A tool to read csv files, transform to json and push to sprint_excel_webserver.
Home-page: https://github.com/heming-langrenn/sprint-excel/tree/main/datapusher
License: Apache-2.0
Author: Stig B. Dørmænen
Author-email: stigbd@gmail.com
Requires-Python: >=3.7,<4.0
Classifier: License :: OSI Approved :: Apache Software License
Classifier: Operating System :: OS Independent
Classifier: Programming Language :: Python :: 3
Classifier: Programming Language :: Python :: 3.7
Classifier: Programming Language :: Python :: 3.8
Classifier: Programming Language :: Python :: 3.9
Requires-Dist: PyYAML (>=5.3.1,<6.0.0)
Requires-Dist: click (>=7.1.2,<8.0.0)
Requires-Dist: jsonpickle (>=1.4.1,<2.0.0)
Requires-Dist: pandas (>=1.1.5,<2.0.0)
Requires-Dist: python-dotenv (>=0.15.0,<0.16.0)
Requires-Dist: requests (>=2.25.1,<3.0.0)
Requires-Dist: watchdog (>=1.0.1,<2.0.0)
Project-URL: Repository, https://github.com/heming-langrenn/sprint-excel
